README.md
randomhash/__init__.py
randomhash/abstract.py
randomhash/helpers.py
randomhash/implemented.py
randomhash-0.6.0.dist-info/LICENSE
randomhash-0.6.0.dist-info/WHEEL
randomhash-0.6.0.dist-info/METADATA
randomhash-0.6.0.dist-info/RECORD
