Metadata-Version: 2.1
Name: randomhash
Version: 0.6.0
Summary: A simple, time-tested, family of random hash functions in Python, based on CRC32 and xxHash, affine transformations, and the Mersenne Twister.
Home-page: https://github.com/jlumbroso/python-random-hash
License: LGPL-3.0-or-later
Author: Jérémie Lumbroso
Author-email: lumbroso@cs.princeton.edu
Requires-Python: >=3.8,<4.0
Classifier: Development Status :: 3 - Alpha
Classifier: License :: OSI Approved :: GNU Lesser General Public License v3 or later (LGPLv3+)
Classifier: Programming Language :: Python :: 3
Classifier: Programming Language :: Python :: 3.10
Classifier: Programming Language :: Python :: 3.8
Classifier: Programming Language :: Python :: 3.9
Classifier: Topic :: Software Development :: Libraries :: Python Modules
Requires-Dist: xxhash (>=3.0.0,<4.0.0)
Project-URL: Repository, https://github.com/jlumbroso/python-random-hash
